{"SimulationConfig":{"name":"experiment_bb27c42a","TimesToRun":0,"config":{"DurationSeconds":60,"EventsGenerator":{"Delay":"00:00:00.0010000","TotalEventsAmount":2500,"InitialProcessorName":"template-filling"},"Validation":{"MaxQueue":2147483647,"ValidationFailureChance":0.1,"RoutingFailureChance":1E-05,"SuccessChance":0.8999900000000001},"TemplateFilling":{"MaxQueue":2147483647,"ValidationFailureChance":0.1,"RoutingFailureChance":1E-05,"SuccessChance":0.8999900000000001},"Prioritization":{"MaxQueue":2147483647,"ValidationFailureChance":0.1,"RoutingFailureChance":1E-05,"SuccessChance":0.8999900000000001},"TransportHub":{"MaxQueue":2147483647,"ValidationFailureChance":0.1,"RoutingFailureChance":1E-05,"SuccessChance":0.8999900000000001}}},"Timestamp":"12:42 AM","Result":[{"Processor":{"ProcessorId":"a0ab9d7a-8856-4e39-b558-4aa8264d6fd9","ProcessorName":"template-filling","TotalQueueSize":842,"QueueSizeObservations":960,"TotalLoadTime":42806.0,"LoadTimeObservations":960,"MeadQueueLength":0.8770833333333333,"MeanLoadTime":44.58958333333333},"Router":{"ProcessorName":"template-filling","TotalRoutedEvents":962,"FailedEvents":0,"SuccessEvents":962,"MeanFailChance":0.0}},{"Processor":{"ProcessorId":"9a87f430-c2e5-4ac5-89fe-bb5e5ffb417c","ProcessorName":"template-filling_dlq","TotalQueueSize":0,"QueueSizeObservations":0,"TotalLoadTime":0.0,"LoadTimeObservations":0,"MeadQueueLength":0.0,"MeanLoadTime":0.0},"Router":{"ProcessorName":"template-filling_dlq","TotalRoutedEvents":0,"FailedEvents":0,"SuccessEvents":0,"MeanFailChance":0.0}},{"Processor":{"ProcessorId":"1a78dbd8-c834-4d75-b8f7-d640de962287","ProcessorName":"template-filling_failed","TotalQueueSize":0,"QueueSizeObservations":94,"TotalLoadTime":0.0,"LoadTimeObservations":94,"MeadQueueLength":0.0,"MeanLoadTime":0.0},"Router":{"ProcessorName":"template-filling_failed","TotalRoutedEvents":95,"FailedEvents":0,"SuccessEvents":95,"MeanFailChance":0.0}},{"Processor":{"ProcessorId":"25c78cc0-035a-44f1-ae01-19c90ff1acfd","ProcessorName":"template-filling_passed","TotalQueueSize":0,"QueueSizeObservations":866,"TotalLoadTime":0.0,"LoadTimeObservations":866,"MeadQueueLength":0.0,"MeanLoadTime":0.0},"Router":{"ProcessorName":"template-filling_passed","TotalRoutedEvents":867,"FailedEvents":0,"SuccessEvents":867,"MeanFailChance":0.0}},{"Processor":{"ProcessorId":"d125faad-cd25-4359-b0ed-2c717fcbb8b7","ProcessorName":"validation","TotalQueueSize":447,"QueueSizeObservations":866,"TotalLoadTime":37685.0,"LoadTimeObservations":866,"MeadQueueLength":0.5161662817551963,"MeanLoadTime":43.5161662817552},"Router":{"ProcessorName":"validation","TotalRoutedEvents":867,"FailedEvents":0,"SuccessEvents":867,"MeanFailChance":0.0}},{"Processor":{"ProcessorId":"f9732a87-0534-441f-b097-106f76aa52d8","ProcessorName":"validation_dlq","TotalQueueSize":0,"QueueSizeObservations":0,"TotalLoadTime":0.0,"LoadTimeObservations":0,"MeadQueueLength":0.0,"MeanLoadTime":0.0},"Router":{"ProcessorName":"validation_dlq","TotalRoutedEvents":0,"FailedEvents":0,"SuccessEvents":0,"MeanFailChance":0.0}},{"Processor":{"ProcessorId":"3e2271b6-90df-4f4e-943d-c386d36c3019","ProcessorName":"validation_failed","TotalQueueSize":0,"QueueSizeObservations":87,"TotalLoadTime":0.0,"LoadTimeObservations":87,"MeadQueueLength":0.0,"MeanLoadTime":0.0},"Router":{"ProcessorName":"validation_failed","TotalRoutedEvents":88,"FailedEvents":0,"SuccessEvents":88,"MeanFailChance":0.0}},{"Processor":{"ProcessorId":"729ab3e9-c0ed-40fc-a8a7-9a5be9f4f125","ProcessorName":"validation_passed","TotalQueueSize":0,"QueueSizeObservations":779,"TotalLoadTime":0.0,"LoadTimeObservations":779,"MeadQueueLength":0.0,"MeanLoadTime":0.0},"Router":{"ProcessorName":"validation_passed","TotalRoutedEvents":780,"FailedEvents":0,"SuccessEvents":780,"MeanFailChance":0.0}},{"Processor":{"ProcessorId":"389d15e7-3fae-4a15-b4af-b3d2549c2a3d","ProcessorName":"prioritize","TotalQueueSize":343,"QueueSizeObservations":778,"TotalLoadTime":34691.0,"LoadTimeObservations":778,"MeadQueueLength":0.44087403598971725,"MeanLoadTime":44.58997429305913},"Router":{"ProcessorName":"prioritize","TotalRoutedEvents":780,"FailedEvents":0,"SuccessEvents":780,"MeanFailChance":0.0}},{"Processor":{"ProcessorId":"aec6b8ae-4686-40e6-9efb-79707f64e0b7","ProcessorName":"prioritize_dlq","TotalQueueSize":0,"QueueSizeObservations":0,"TotalLoadTime":0.0,"LoadTimeObservations":0,"MeadQueueLength":0.0,"MeanLoadTime":0.0},"Router":{"ProcessorName":"prioritize_dlq","TotalRoutedEvents":0,"FailedEvents":0,"SuccessEvents":0,"MeanFailChance":0.0}},{"Processor":{"ProcessorId":"104cca8f-dc05-413c-a891-e1b9cde71fd6","ProcessorName":"prioritize_failed","TotalQueueSize":0,"QueueSizeObservations":79,"TotalLoadTime":0.0,"LoadTimeObservations":79,"MeadQueueLength":0.0,"MeanLoadTime":0.0},"Router":{"ProcessorName":"prioritize_failed","TotalRoutedEvents":80,"FailedEvents":0,"SuccessEvents":80,"MeanFailChance":0.0}},{"Processor":{"ProcessorId":"a0a7ba17-0d04-42c8-b91f-a0936e41ea2e","ProcessorName":"prioritize_passed","TotalQueueSize":0,"QueueSizeObservations":699,"TotalLoadTime":0.0,"LoadTimeObservations":699,"MeadQueueLength":0.0,"MeanLoadTime":0.0},"Router":{"ProcessorName":"prioritize_passed","TotalRoutedEvents":700,"FailedEvents":0,"SuccessEvents":700,"MeanFailChance":0.0}},{"Processor":{"ProcessorId":"8ac4b4e2-1af2-4ac4-8371-8a38bc2d36fd","ProcessorName":"transport-hub","TotalQueueSize":266,"QueueSizeObservations":699,"TotalLoadTime":31046.0,"LoadTimeObservations":699,"MeadQueueLength":0.3805436337625179,"MeanLoadTime":44.414878397711014},"Router":{"ProcessorName":"transport-hub","TotalRoutedEvents":700,"FailedEvents":0,"SuccessEvents":700,"MeanFailChance":0.0}},{"Processor":{"ProcessorId":"afbb03ce-6798-4e62-8893-e74cbc5ee8af","ProcessorName":"transport-hub_dlq","TotalQueueSize":0,"QueueSizeObservations":0,"TotalLoadTime":0.0,"LoadTimeObservations":0,"MeadQueueLength":0.0,"MeanLoadTime":0.0},"Router":{"ProcessorName":"transport-hub_dlq","TotalRoutedEvents":0,"FailedEvents":0,"SuccessEvents":0,"MeanFailChance":0.0}},{"Processor":{"ProcessorId":"16b171d9-b922-4bfe-8673-c68944a4e3de","ProcessorName":"transport-hub_failed","TotalQueueSize":0,"QueueSizeObservations":65,"TotalLoadTime":0.0,"LoadTimeObservations":65,"MeadQueueLength":0.0,"MeanLoadTime":0.0},"Router":{"ProcessorName":"transport-hub_failed","TotalRoutedEvents":66,"FailedEvents":0,"SuccessEvents":66,"MeanFailChance":0.0}},{"Processor":{"ProcessorId":"7d9139ec-e1fb-4e6b-b748-e16ffdcc95ba","ProcessorName":"transport-hub_passed","TotalQueueSize":0,"QueueSizeObservations":634,"TotalLoadTime":0.0,"LoadTimeObservations":634,"MeadQueueLength":0.0,"MeanLoadTime":0.0},"Router":{"ProcessorName":"transport-hub_passed","TotalRoutedEvents":635,"FailedEvents":0,"SuccessEvents":635,"MeanFailChance":0.0}}]}