{"SimulationConfig":{"name":"experiment_e3afbb67","TimesToRun":0,"config":{"DurationSeconds":60,"EventsGenerator":{"Delay":"00:00:00.0010000","TotalEventsAmount":2500,"InitialProcessorName":"template-filling"},"Validation":{"MaxQueue":2147483647,"ValidationFailureChance":0.1,"RoutingFailureChance":1E-05,"SuccessChance":0.8999900000000001},"TemplateFilling":{"MaxQueue":2147483647,"ValidationFailureChance":0.1,"RoutingFailureChance":1E-05,"SuccessChance":0.8999900000000001},"Prioritization":{"MaxQueue":2147483647,"ValidationFailureChance":0.1,"RoutingFailureChance":1E-05,"SuccessChance":0.8999900000000001},"TransportHub":{"MaxQueue":2147483647,"ValidationFailureChance":0.1,"RoutingFailureChance":1E-05,"SuccessChance":0.8999900000000001}}},"Timestamp":"12:41 AM","Result":[{"Processor":{"ProcessorId":"7794cc87-c4e0-4cbd-a84e-e0f7f3da16e3","ProcessorName":"template-filling","TotalQueueSize":890,"QueueSizeObservations":963,"TotalLoadTime":43238.0,"LoadTimeObservations":963,"MeadQueueLength":0.9241952232606438,"MeanLoadTime":44.89927310488058},"Router":{"ProcessorName":"template-filling","TotalRoutedEvents":965,"FailedEvents":0,"SuccessEvents":965,"MeanFailChance":0.0}},{"Processor":{"ProcessorId":"16cef6e0-133a-49fc-a38b-0b8ae39bcbe4","ProcessorName":"template-filling_dlq","TotalQueueSize":0,"QueueSizeObservations":0,"TotalLoadTime":0.0,"LoadTimeObservations":0,"MeadQueueLength":0.0,"MeanLoadTime":0.0},"Router":{"ProcessorName":"template-filling_dlq","TotalRoutedEvents":0,"FailedEvents":0,"SuccessEvents":0,"MeanFailChance":0.0}},{"Processor":{"ProcessorId":"d1917954-b014-48e8-8911-2615c9016b21","ProcessorName":"template-filling_failed","TotalQueueSize":0,"QueueSizeObservations":94,"TotalLoadTime":0.0,"LoadTimeObservations":94,"MeadQueueLength":0.0,"MeanLoadTime":0.0},"Router":{"ProcessorName":"template-filling_failed","TotalRoutedEvents":95,"FailedEvents":0,"SuccessEvents":95,"MeanFailChance":0.0}},{"Processor":{"ProcessorId":"eee606b9-a29f-4cff-b0bf-6f9ab20804bc","ProcessorName":"template-filling_passed","TotalQueueSize":0,"QueueSizeObservations":869,"TotalLoadTime":0.0,"LoadTimeObservations":869,"MeadQueueLength":0.0,"MeanLoadTime":0.0},"Router":{"ProcessorName":"template-filling_passed","TotalRoutedEvents":870,"FailedEvents":0,"SuccessEvents":870,"MeanFailChance":0.0}},{"Processor":{"ProcessorId":"47a0646e-9244-4224-8bd0-66222c132d0a","ProcessorName":"validation","TotalQueueSize":535,"QueueSizeObservations":867,"TotalLoadTime":39171.0,"LoadTimeObservations":867,"MeadQueueLength":0.6170703575547867,"MeanLoadTime":45.17993079584775},"Router":{"ProcessorName":"validation","TotalRoutedEvents":870,"FailedEvents":0,"SuccessEvents":870,"MeanFailChance":0.0}},{"Processor":{"ProcessorId":"9413f1c4-80a4-41a3-83f0-dd0c8325da15","ProcessorName":"validation_dlq","TotalQueueSize":0,"QueueSizeObservations":0,"TotalLoadTime":0.0,"LoadTimeObservations":0,"MeadQueueLength":0.0,"MeanLoadTime":0.0},"Router":{"ProcessorName":"validation_dlq","TotalRoutedEvents":0,"FailedEvents":0,"SuccessEvents":0,"MeanFailChance":0.0}},{"Processor":{"ProcessorId":"fb8ac2e7-3282-411f-8142-759f1db0c124","ProcessorName":"validation_failed","TotalQueueSize":0,"QueueSizeObservations":85,"TotalLoadTime":0.0,"LoadTimeObservations":85,"MeadQueueLength":0.0,"MeanLoadTime":0.0},"Router":{"ProcessorName":"validation_failed","TotalRoutedEvents":86,"FailedEvents":0,"SuccessEvents":86,"MeanFailChance":0.0}},{"Processor":{"ProcessorId":"c2db697d-541e-40c2-b81f-a82bd1edfe84","ProcessorName":"validation_passed","TotalQueueSize":0,"QueueSizeObservations":782,"TotalLoadTime":0.0,"LoadTimeObservations":782,"MeadQueueLength":0.0,"MeanLoadTime":0.0},"Router":{"ProcessorName":"validation_passed","TotalRoutedEvents":783,"FailedEvents":0,"SuccessEvents":783,"MeanFailChance":0.0}},{"Processor":{"ProcessorId":"8b587a7c-c4eb-48c6-9607-54a22bc128c2","ProcessorName":"prioritize","TotalQueueSize":329,"QueueSizeObservations":782,"TotalLoadTime":34921.0,"LoadTimeObservations":782,"MeadQueueLength":0.42071611253196933,"MeanLoadTime":44.65601023017903},"Router":{"ProcessorName":"prioritize","TotalRoutedEvents":783,"FailedEvents":0,"SuccessEvents":783,"MeanFailChance":0.0}},{"Processor":{"ProcessorId":"f9b5be2a-c099-4f28-a252-42eaacc6f629","ProcessorName":"prioritize_dlq","TotalQueueSize":0,"QueueSizeObservations":0,"TotalLoadTime":0.0,"LoadTimeObservations":0,"MeadQueueLength":0.0,"MeanLoadTime":0.0},"Router":{"ProcessorName":"prioritize_dlq","TotalRoutedEvents":0,"FailedEvents":0,"SuccessEvents":0,"MeanFailChance":0.0}},{"Processor":{"ProcessorId":"811f38c1-77df-40b0-9da7-3538afd473da","ProcessorName":"prioritize_failed","TotalQueueSize":0,"QueueSizeObservations":76,"TotalLoadTime":0.0,"LoadTimeObservations":76,"MeadQueueLength":0.0,"MeanLoadTime":0.0},"Router":{"ProcessorName":"prioritize_failed","TotalRoutedEvents":77,"FailedEvents":0,"SuccessEvents":77,"MeanFailChance":0.0}},{"Processor":{"ProcessorId":"8e07ae63-63c0-44cd-8e15-16b51f44bf41","ProcessorName":"prioritize_passed","TotalQueueSize":0,"QueueSizeObservations":706,"TotalLoadTime":0.0,"LoadTimeObservations":706,"MeadQueueLength":0.0,"MeanLoadTime":0.0},"Router":{"ProcessorName":"prioritize_passed","TotalRoutedEvents":707,"FailedEvents":0,"SuccessEvents":707,"MeanFailChance":0.0}},{"Processor":{"ProcessorId":"7d7ba83c-9e38-46b7-a5a2-b5402727643f","ProcessorName":"transport-hub","TotalQueueSize":236,"QueueSizeObservations":706,"TotalLoadTime":31560.0,"LoadTimeObservations":706,"MeadQueueLength":0.3342776203966006,"MeanLoadTime":44.70254957507082},"Router":{"ProcessorName":"transport-hub","TotalRoutedEvents":707,"FailedEvents":0,"SuccessEvents":707,"MeanFailChance":0.0}},{"Processor":{"ProcessorId":"d6e5ecd6-c7ac-4d60-9cd2-a642685204a0","ProcessorName":"transport-hub_dlq","TotalQueueSize":0,"QueueSizeObservations":0,"TotalLoadTime":0.0,"LoadTimeObservations":0,"MeadQueueLength":0.0,"MeanLoadTime":0.0},"Router":{"ProcessorName":"transport-hub_dlq","TotalRoutedEvents":0,"FailedEvents":0,"SuccessEvents":0,"MeanFailChance":0.0}},{"Processor":{"ProcessorId":"61f73e2d-8a78-44fd-8865-e118120e56f0","ProcessorName":"transport-hub_failed","TotalQueueSize":0,"QueueSizeObservations":67,"TotalLoadTime":0.0,"LoadTimeObservations":67,"MeadQueueLength":0.0,"MeanLoadTime":0.0},"Router":{"ProcessorName":"transport-hub_failed","TotalRoutedEvents":68,"FailedEvents":0,"SuccessEvents":68,"MeanFailChance":0.0}},{"Processor":{"ProcessorId":"e30edfa3-0d7f-40f1-87be-26d006bf5a33","ProcessorName":"transport-hub_passed","TotalQueueSize":0,"QueueSizeObservations":639,"TotalLoadTime":0.0,"LoadTimeObservations":639,"MeadQueueLength":0.0,"MeanLoadTime":0.0},"Router":{"ProcessorName":"transport-hub_passed","TotalRoutedEvents":640,"FailedEvents":0,"SuccessEvents":640,"MeanFailChance":0.0}}]}