{"SimulationConfig":{"name":"experiment_e88ca302","TimesToRun":0,"config":{"DurationSeconds":10,"EventsGenerator":{"Delay":"00:00:00.0050000","TotalEventsAmount":1000,"InitialProcessorName":"template-filling"},"Validation":{"MaxQueue":2147483647,"ValidationFailureChance":0.1,"RoutingFailureChance":1E-05,"SuccessChance":0.8999900000000001},"TemplateFilling":{"MaxQueue":2147483647,"ValidationFailureChance":0.1,"RoutingFailureChance":1E-05,"SuccessChance":0.8999900000000001},"Prioritization":{"MaxQueue":2147483647,"ValidationFailureChance":0.1,"RoutingFailureChance":1E-05,"SuccessChance":0.8999900000000001},"TransportHub":{"MaxQueue":2147483647,"ValidationFailureChance":0.1,"RoutingFailureChance":1E-05,"SuccessChance":0.8999900000000001}}},"Timestamp":"11:10 PM","Result":[{"Processor":{"ProcessorId":"85d21465-2dda-4bee-9817-e93548c15157","ProcessorName":"template-filling","TotalQueueSize":162,"QueueSizeObservations":163,"TotalLoadTime":6995.0,"LoadTimeObservations":163,"MeadQueueLength":0.9938650306748467,"MeanLoadTime":42.91411042944785},"Router":{"ProcessorName":"template-filling","TotalRoutedEvents":165,"FailedEvents":0,"SuccessEvents":165,"MeanFailChance":0.0}},{"Processor":{"ProcessorId":"f0e23096-7583-45ef-a611-f8f9c6802a4b","ProcessorName":"template-filling_dlq","TotalQueueSize":0,"QueueSizeObservations":0,"TotalLoadTime":0.0,"LoadTimeObservations":0,"MeadQueueLength":0.0,"MeanLoadTime":0.0},"Router":{"ProcessorName":"template-filling_dlq","TotalRoutedEvents":0,"FailedEvents":0,"SuccessEvents":0,"MeanFailChance":0.0}},{"Processor":{"ProcessorId":"e6d160b7-aeb0-4ac9-be31-58c2a788d3e8","ProcessorName":"template-filling_failed","TotalQueueSize":0,"QueueSizeObservations":17,"TotalLoadTime":0.0,"LoadTimeObservations":17,"MeadQueueLength":0.0,"MeanLoadTime":0.0},"Router":{"ProcessorName":"template-filling_failed","TotalRoutedEvents":18,"FailedEvents":0,"SuccessEvents":18,"MeanFailChance":0.0}},{"Processor":{"ProcessorId":"841683ce-c596-48d0-b53a-847f219a33f9","ProcessorName":"template-filling_passed","TotalQueueSize":0,"QueueSizeObservations":146,"TotalLoadTime":0.0,"LoadTimeObservations":146,"MeadQueueLength":0.0,"MeanLoadTime":0.0},"Router":{"ProcessorName":"template-filling_passed","TotalRoutedEvents":147,"FailedEvents":0,"SuccessEvents":147,"MeanFailChance":0.0}},{"Processor":{"ProcessorId":"8da38f94-7f30-4774-8129-449b7431c4d1","ProcessorName":"validation","TotalQueueSize":86,"QueueSizeObservations":146,"TotalLoadTime":6846.0,"LoadTimeObservations":146,"MeadQueueLength":0.589041095890411,"MeanLoadTime":46.89041095890411},"Router":{"ProcessorName":"validation","TotalRoutedEvents":147,"FailedEvents":0,"SuccessEvents":147,"MeanFailChance":0.0}},{"Processor":{"ProcessorId":"70ae9ae0-b36a-4811-be84-6fe4044d5898","ProcessorName":"validation_dlq","TotalQueueSize":0,"QueueSizeObservations":0,"TotalLoadTime":0.0,"LoadTimeObservations":0,"MeadQueueLength":0.0,"MeanLoadTime":0.0},"Router":{"ProcessorName":"validation_dlq","TotalRoutedEvents":0,"FailedEvents":0,"SuccessEvents":0,"MeanFailChance":0.0}},{"Processor":{"ProcessorId":"64e23145-0937-4d7b-b435-f6aedb471aed","ProcessorName":"validation_failed","TotalQueueSize":0,"QueueSizeObservations":19,"TotalLoadTime":0.0,"LoadTimeObservations":19,"MeadQueueLength":0.0,"MeanLoadTime":0.0},"Router":{"ProcessorName":"validation_failed","TotalRoutedEvents":20,"FailedEvents":0,"SuccessEvents":20,"MeanFailChance":0.0}},{"Processor":{"ProcessorId":"a2ea3b52-2e53-49ef-96a1-8709ae6907a1","ProcessorName":"validation_passed","TotalQueueSize":0,"QueueSizeObservations":127,"TotalLoadTime":0.0,"LoadTimeObservations":127,"MeadQueueLength":0.0,"MeanLoadTime":0.0},"Router":{"ProcessorName":"validation_passed","TotalRoutedEvents":128,"FailedEvents":0,"SuccessEvents":128,"MeanFailChance":0.0}},{"Processor":{"ProcessorId":"9c3961c5-f56f-48c1-aa6f-cf272b6303c8","ProcessorName":"prioritize","TotalQueueSize":45,"QueueSizeObservations":127,"TotalLoadTime":5679.0,"LoadTimeObservations":127,"MeadQueueLength":0.3543307086614173,"MeanLoadTime":44.71653543307087},"Router":{"ProcessorName":"prioritize","TotalRoutedEvents":128,"FailedEvents":0,"SuccessEvents":128,"MeanFailChance":0.0}},{"Processor":{"ProcessorId":"bee63463-b811-4289-9cd9-e3e4c4d54d35","ProcessorName":"prioritize_dlq","TotalQueueSize":0,"QueueSizeObservations":0,"TotalLoadTime":0.0,"LoadTimeObservations":0,"MeadQueueLength":0.0,"MeanLoadTime":0.0},"Router":{"ProcessorName":"prioritize_dlq","TotalRoutedEvents":0,"FailedEvents":0,"SuccessEvents":0,"MeanFailChance":0.0}},{"Processor":{"ProcessorId":"3f0ea805-a081-47e4-baa2-2d040286dcde","ProcessorName":"prioritize_failed","TotalQueueSize":0,"QueueSizeObservations":11,"TotalLoadTime":0.0,"LoadTimeObservations":11,"MeadQueueLength":0.0,"MeanLoadTime":0.0},"Router":{"ProcessorName":"prioritize_failed","TotalRoutedEvents":12,"FailedEvents":0,"SuccessEvents":12,"MeanFailChance":0.0}},{"Processor":{"ProcessorId":"7e8a8373-94e9-4076-b81d-149468101599","ProcessorName":"prioritize_passed","TotalQueueSize":0,"QueueSizeObservations":116,"TotalLoadTime":0.0,"LoadTimeObservations":116,"MeadQueueLength":0.0,"MeanLoadTime":0.0},"Router":{"ProcessorName":"prioritize_passed","TotalRoutedEvents":117,"FailedEvents":0,"SuccessEvents":117,"MeanFailChance":0.0}},{"Processor":{"ProcessorId":"b1fa8219-be58-40ca-9ce3-cf0f71298239","ProcessorName":"transport-hub","TotalQueueSize":45,"QueueSizeObservations":116,"TotalLoadTime":5226.0,"LoadTimeObservations":116,"MeadQueueLength":0.3879310344827586,"MeanLoadTime":45.05172413793103},"Router":{"ProcessorName":"transport-hub","TotalRoutedEvents":117,"FailedEvents":0,"SuccessEvents":117,"MeanFailChance":0.0}},{"Processor":{"ProcessorId":"e972657a-551f-4e58-8f07-272cad101514","ProcessorName":"transport-hub_dlq","TotalQueueSize":0,"QueueSizeObservations":0,"TotalLoadTime":0.0,"LoadTimeObservations":0,"MeadQueueLength":0.0,"MeanLoadTime":0.0},"Router":{"ProcessorName":"transport-hub_dlq","TotalRoutedEvents":0,"FailedEvents":0,"SuccessEvents":0,"MeanFailChance":0.0}},{"Processor":{"ProcessorId":"357d87aa-14e8-4875-9779-68930b04e4f0","ProcessorName":"transport-hub_failed","TotalQueueSize":0,"QueueSizeObservations":9,"TotalLoadTime":0.0,"LoadTimeObservations":9,"MeadQueueLength":0.0,"MeanLoadTime":0.0},"Router":{"ProcessorName":"transport-hub_failed","TotalRoutedEvents":10,"FailedEvents":0,"SuccessEvents":10,"MeanFailChance":0.0}},{"Processor":{"ProcessorId":"f98b1231-db81-4a60-9787-2ae03fb700ed","ProcessorName":"transport-hub_passed","TotalQueueSize":0,"QueueSizeObservations":107,"TotalLoadTime":0.0,"LoadTimeObservations":107,"MeadQueueLength":0.0,"MeanLoadTime":0.0},"Router":{"ProcessorName":"transport-hub_passed","TotalRoutedEvents":108,"FailedEvents":0,"SuccessEvents":108,"MeanFailChance":0.0}}]}