{"SimulationConfig":{"name":"experiment_7c7fa53b","TimesToRun":0,"config":{"DurationSeconds":60,"EventsGenerator":{"Delay":"00:00:00.0010000","TotalEventsAmount":2500,"InitialProcessorName":"template-filling"},"Validation":{"MaxQueue":2147483647,"ValidationFailureChance":0.1,"RoutingFailureChance":1E-05,"SuccessChance":0.8999900000000001},"TemplateFilling":{"MaxQueue":2147483647,"ValidationFailureChance":0.1,"RoutingFailureChance":1E-05,"SuccessChance":0.8999900000000001},"Prioritization":{"MaxQueue":2147483647,"ValidationFailureChance":0.1,"RoutingFailureChance":1E-05,"SuccessChance":0.8999900000000001},"TransportHub":{"MaxQueue":2147483647,"ValidationFailureChance":0.1,"RoutingFailureChance":1E-05,"SuccessChance":0.8999900000000001}}},"Timestamp":"11:48 PM","Result":[{"Processor":{"ProcessorId":"9ac8bc76-5ca0-4b17-bc83-6d3e9d37ba6a","ProcessorName":"template-filling","TotalQueueSize":1384,"QueueSizeObservations":1006,"TotalLoadTime":45404.0,"LoadTimeObservations":1006,"MeadQueueLength":1.3757455268389662,"MeanLoadTime":45.133200795228625},"Router":{"ProcessorName":"template-filling","TotalRoutedEvents":1010,"FailedEvents":0,"SuccessEvents":1010,"MeanFailChance":0.0}},{"Processor":{"ProcessorId":"f4621eeb-57a0-437e-b151-b97a1c538be6","ProcessorName":"template-filling_dlq","TotalQueueSize":0,"QueueSizeObservations":0,"TotalLoadTime":0.0,"LoadTimeObservations":0,"MeadQueueLength":0.0,"MeanLoadTime":0.0},"Router":{"ProcessorName":"template-filling_dlq","TotalRoutedEvents":0,"FailedEvents":0,"SuccessEvents":0,"MeanFailChance":0.0}},{"Processor":{"ProcessorId":"e35896fd-0188-46a5-a6fa-b2fb63b36d3c","ProcessorName":"template-filling_failed","TotalQueueSize":0,"QueueSizeObservations":101,"TotalLoadTime":0.0,"LoadTimeObservations":101,"MeadQueueLength":0.0,"MeanLoadTime":0.0},"Router":{"ProcessorName":"template-filling_failed","TotalRoutedEvents":102,"FailedEvents":0,"SuccessEvents":102,"MeanFailChance":0.0}},{"Processor":{"ProcessorId":"e8049ce5-a8b4-454f-b3f6-c48acd9e2ea6","ProcessorName":"template-filling_passed","TotalQueueSize":0,"QueueSizeObservations":905,"TotalLoadTime":0.0,"LoadTimeObservations":905,"MeadQueueLength":0.0,"MeanLoadTime":0.0},"Router":{"ProcessorName":"template-filling_passed","TotalRoutedEvents":906,"FailedEvents":0,"SuccessEvents":906,"MeanFailChance":0.0}},{"Processor":{"ProcessorId":"1c78a665-059f-4990-bf7d-4261f5dfe531","ProcessorName":"validation","TotalQueueSize":675,"QueueSizeObservations":903,"TotalLoadTime":40841.0,"LoadTimeObservations":903,"MeadQueueLength":0.7475083056478405,"MeanLoadTime":45.2281284606866},"Router":{"ProcessorName":"validation","TotalRoutedEvents":906,"FailedEvents":0,"SuccessEvents":906,"MeanFailChance":0.0}},{"Processor":{"ProcessorId":"b4dab9d3-7629-49b3-954d-c6ddaa0839b8","ProcessorName":"validation_dlq","TotalQueueSize":0,"QueueSizeObservations":0,"TotalLoadTime":0.0,"LoadTimeObservations":0,"MeadQueueLength":0.0,"MeanLoadTime":0.0},"Router":{"ProcessorName":"validation_dlq","TotalRoutedEvents":0,"FailedEvents":0,"SuccessEvents":0,"MeanFailChance":0.0}},{"Processor":{"ProcessorId":"1bbde85f-ef94-40a8-a787-177cf86c7f24","ProcessorName":"validation_failed","TotalQueueSize":0,"QueueSizeObservations":92,"TotalLoadTime":0.0,"LoadTimeObservations":92,"MeadQueueLength":0.0,"MeanLoadTime":0.0},"Router":{"ProcessorName":"validation_failed","TotalRoutedEvents":93,"FailedEvents":0,"SuccessEvents":93,"MeanFailChance":0.0}},{"Processor":{"ProcessorId":"5e57187c-2ae1-4d17-a439-0974b073650e","ProcessorName":"validation_passed","TotalQueueSize":0,"QueueSizeObservations":811,"TotalLoadTime":0.0,"LoadTimeObservations":811,"MeadQueueLength":0.0,"MeanLoadTime":0.0},"Router":{"ProcessorName":"validation_passed","TotalRoutedEvents":812,"FailedEvents":0,"SuccessEvents":812,"MeanFailChance":0.0}},{"Processor":{"ProcessorId":"a6882e1f-f4c6-4d22-8138-3dc99ce8af72","ProcessorName":"prioritize","TotalQueueSize":393,"QueueSizeObservations":811,"TotalLoadTime":36274.0,"LoadTimeObservations":811,"MeadQueueLength":0.4845869297163995,"MeanLoadTime":44.72749691738594},"Router":{"ProcessorName":"prioritize","TotalRoutedEvents":812,"FailedEvents":0,"SuccessEvents":812,"MeanFailChance":0.0}},{"Processor":{"ProcessorId":"54225ef4-9d67-4aef-84e3-b97d03d8d9a2","ProcessorName":"prioritize_dlq","TotalQueueSize":0,"QueueSizeObservations":0,"TotalLoadTime":0.0,"LoadTimeObservations":0,"MeadQueueLength":0.0,"MeanLoadTime":0.0},"Router":{"ProcessorName":"prioritize_dlq","TotalRoutedEvents":0,"FailedEvents":0,"SuccessEvents":0,"MeanFailChance":0.0}},{"Processor":{"ProcessorId":"379ab2d3-0dea-4bb7-8d61-968acd610c54","ProcessorName":"prioritize_failed","TotalQueueSize":0,"QueueSizeObservations":72,"TotalLoadTime":0.0,"LoadTimeObservations":72,"MeadQueueLength":0.0,"MeanLoadTime":0.0},"Router":{"ProcessorName":"prioritize_failed","TotalRoutedEvents":73,"FailedEvents":0,"SuccessEvents":73,"MeanFailChance":0.0}},{"Processor":{"ProcessorId":"2279589a-0eb4-443d-9bed-073edfc1df7a","ProcessorName":"prioritize_passed","TotalQueueSize":0,"QueueSizeObservations":739,"TotalLoadTime":0.0,"LoadTimeObservations":739,"MeadQueueLength":0.0,"MeanLoadTime":0.0},"Router":{"ProcessorName":"prioritize_passed","TotalRoutedEvents":740,"FailedEvents":0,"SuccessEvents":740,"MeanFailChance":0.0}},{"Processor":{"ProcessorId":"ff39838d-546c-4d1f-8865-a954444dec99","ProcessorName":"transport-hub","TotalQueueSize":255,"QueueSizeObservations":738,"TotalLoadTime":33131.0,"LoadTimeObservations":738,"MeadQueueLength":0.34552845528455284,"MeanLoadTime":44.892953929539296},"Router":{"ProcessorName":"transport-hub","TotalRoutedEvents":739,"FailedEvents":0,"SuccessEvents":739,"MeanFailChance":0.0}},{"Processor":{"ProcessorId":"c1ba2199-ca7d-496d-bea1-d43d1b099259","ProcessorName":"transport-hub_dlq","TotalQueueSize":0,"QueueSizeObservations":0,"TotalLoadTime":0.0,"LoadTimeObservations":0,"MeadQueueLength":0.0,"MeanLoadTime":0.0},"Router":{"ProcessorName":"transport-hub_dlq","TotalRoutedEvents":0,"FailedEvents":0,"SuccessEvents":0,"MeanFailChance":0.0}},{"Processor":{"ProcessorId":"bd3dc08a-e2b6-45cc-8334-9faf028c9b69","ProcessorName":"transport-hub_failed","TotalQueueSize":0,"QueueSizeObservations":67,"TotalLoadTime":0.0,"LoadTimeObservations":67,"MeadQueueLength":0.0,"MeanLoadTime":0.0},"Router":{"ProcessorName":"transport-hub_failed","TotalRoutedEvents":68,"FailedEvents":0,"SuccessEvents":68,"MeanFailChance":0.0}},{"Processor":{"ProcessorId":"28495c92-fa9a-445d-a1f9-30ec146ebc29","ProcessorName":"transport-hub_passed","TotalQueueSize":0,"QueueSizeObservations":671,"TotalLoadTime":0.0,"LoadTimeObservations":671,"MeadQueueLength":0.0,"MeanLoadTime":0.0},"Router":{"ProcessorName":"transport-hub_passed","TotalRoutedEvents":672,"FailedEvents":0,"SuccessEvents":672,"MeanFailChance":0.0}}]}